xcsv/plot_map/__init__.py
xcsv/plot_map/__main__.py
xcsv_plot_map-0.4.2.dist-info/entry_points.txt
xcsv_plot_map-0.4.2.dist-info/LICENSE
xcsv_plot_map-0.4.2.dist-info/WHEEL
xcsv_plot_map-0.4.2.dist-info/METADATA
xcsv_plot_map-0.4.2.dist-info/RECORD
