Metadata-Version: 2.1
Name: xcsv-plot-map
Version: 0.4.2
Summary: Subpackage to plot and locate on a map, data from extended CSV (XCSV) files
Home-page: https://github.com/paul-breen/xcsv-plot-map
License: Apache-2.0
Author: Paul Breen
Author-email: pbree@bas.ac.uk
Requires-Python: >=3.8,<3.11
Classifier: License :: OSI Approved :: Apache Software License
Classifier: Programming Language :: Python :: 3
Classifier: Programming Language :: Python :: 3.8
Classifier: Programming Language :: Python :: 3.9
Classifier: Programming Language :: Python :: 3.10
Requires-Dist: Cartopy (>=0.21.1,<0.22.0)
Requires-Dist: matplotlib (>=3.5.2,<4.0.0)
Requires-Dist: scipy (>=1.8.1,<2.0.0)
Requires-Dist: shapely (>=2.0.1,<3.0.0)
Requires-Dist: xcsv-plot (>=0,<1)
Project-URL: Documentation, https://github.com/paul-breen/xcsv-plot-map/blob/main/README.md
Project-URL: Repository, https://github.com/paul-breen/xcsv-plot-map
